{
  "metadata": {
    "version": 2,
    "www_path_prefix": "http://www.crunchbase.com/",
    "api_path_prefix": "http://api.crunchbase.com/v/2/",
    "image_path_prefix": "https://res.cloudinary.com/crunchbase-production/"
  },
  "data": {
    "uuid": "bf1b2365137bb6e8151ece01ee81abd6",
    "type": "Organization",
    "properties": {
      "short_description": "Altoros provides big data expertise and PaaS-based enablement for software vendors, IaaS providers and information-based enterprises.",
      "permalink": "altoros-systems",
      "primary_role": "company",
      "is_closed": false,
      "closed_on_trust_code": 0,
      "homepage_url": "http://www.altoros.com",
      "name": "Altoros",
      "closed_on_day": null,
      "closed_on_month": null,
      "closed_on_year": null,
      "closed_on": null,
      "role_company": true,
      "num_employees_max": 250,
      "num_employees_min": 101,
      "email_address": "engineering@altoros.com",
      "description": "Altoros provides big data expertise and Platform-as-a-Service enablement to software vendors, IaaS providers, and information-heavy enterprises. Headquartered in Silicon Valley (Sunnyvale, California), Altoros is a 250+ employee team across 8 locations (California, Massachusetts, Norway, Denmark, UK, Switzerland, Argentina, and Eastern Europe). The company has a proven track record serving technology leaders, such as RightScale, Couchbase, NuoDB, Joyent, Cisco, and other businesses across various industries. For more, please visit www.altoros.com.\n",
      "founded_on_day": 1,
      "founded_on_trust_code": 4,
      "founded_on_month": 1,
      "founded_on_year": 2001,
      "founded_on": "2001-01-01",
      "created_at": 1279829869,
      "updated_at": 1409879242,
      "total_funding_usd": 0,
      "number_of_investments": 0,
      "number_of_employees": 250
    },
    "relationships": {
      "past_team": {
        "paging": {
          "total_items": 1,
          "first_page_url": "http://api.crunchbase.com/v/2/organization/altoros-systems/past_team",
          "sort_order": "created_at DESC"
        },
        "items": [
          {
            "first_name": "Igor",
            "last_name": "Zubchenok",
            "title": "Project Manager",
            "started_on": "2007-11-01",
            "ended_on": "2011-12-01",
            "path": "person/igor-zubchenok",
            "created_at": 1374516972,
            "updated_at": 1397989340
          }
        ]
      },
      "current_team": {
        "paging": {
          "total_items": 7,
          "first_page_url": "http://api.crunchbase.com/v/2/organization/altoros-systems/current_team",
          "sort_order": "custom"
        },
        "items": [
          {
            "first_name": "Michael",
            "last_name": "Brandmaier",
            "title": "Managing Director Switzerland",
            "started_on": "2012-08-01",
            "path": "person/michael-brandmaier",
            "created_at": 1378928196,
            "updated_at": 1397989400
          },
          {
            "first_name": "Robert",
            "last_name": "Claeson",
            "title": "Managing Director UK",
            "started_on": "2012-06-01",
            "path": "person/robert-claeson",
            "created_at": 1378928196,
            "updated_at": 1397989399
          },
          {
            "first_name": "Glenn",
            "last_name": "DiSarcina",
            "title": "Director of Business Development, New England",
            "started_on": "2013-08-01",
            "path": "person/glenn-disarcina",
            "created_at": 1378928196,
            "updated_at": 1397989400
          },
          {
            "first_name": "Kim",
            "last_name": "Jonassen",
            "title": "Managing Director Denmark",
            "started_on": "2011-01-01",
            "path": "person/kim-jonassen",
            "created_at": 1378928196,
            "updated_at": 1397989399
          },
          {
            "first_name": "Renat",
            "last_name": "Khasanshyn",
            "title": "Founder and CEO",
            "started_on": "2001-12-01",
            "path": "person/renat-khasanshyn",
            "created_at": 1297164760,
            "updated_at": 1410041018
          },
          {
            "first_name": "Jan-Terje",
            "last_name": "Nordlien",
            "title": "CEO of Altoros Norge AS",
            "started_on": "2009-10-01",
            "path": "person/jan-terje-nordlien",
            "created_at": 1378928196,
            "updated_at": 1397989399
          },
          {
            "first_name": "Andrei",
            "last_name": "Yurkevich",
            "title": "President and CTO",
            "started_on": "2001-01-01",
            "path": "person/andrei-yurkevich",
            "created_at": 1378928196,
            "updated_at": 1397989399
          }
        ]
      },
      "offices": {
        "paging": {
          "total_items": 5,
          "first_page_url": "http://api.crunchbase.com/v/2/organization/altoros-systems/offices",
          "sort_order": "created_at DESC"
        },
        "items": [
          {
            "type": "Address",
            "name": "Danish Office",
            "street_1": "Vejls\u00f8vej 51, bygning O",
            "street_2": null,
            "postal_code": "DK-8600",
            "city": "Silkeborg",
            "city_path": "location/silkeborg/874001ff81eabf6bc589e9544cc71205",
            "region": "Midtjylland",
            "region_path": "location/midtjylland/f66c7c94243e98c8e652daa117cc2e48",
            "country": "Denmark",
            "country_path": "location/denmark/f593ac31624a2ccda203ddb04c319a79",
            "latitude": null,
            "longitude": null,
            "created_at": 1378901076,
            "updated_at": 1397991873
          },
          {
            "type": "Address",
            "name": "Swiss Office",
            "street_1": "Dufourstrasse 90",
            "street_2": null,
            "postal_code": "8008",
            "city": "Z\u00fcrich",
            "city_path": "location/z\u00fcrich/bd22efa44815cf8ee8c5668079240b6c",
            "region": "Zurich",
            "region_path": "location/zurich/d63a3c1ed300da22915c69b7b8138f75",
            "country": "Switzerland",
            "country_path": "location/switzerland/078d9679a86202a257c88337e9a1eec8",
            "latitude": null,
            "longitude": null,
            "created_at": 1378901076,
            "updated_at": 1397991873
          },
          {
            "type": "Address",
            "name": "UK Office",
            "street_1": "Unit 14, 19-21 Crawford St.",
            "street_2": null,
            "postal_code": "W1H 1PJ",
            "city": "London",
            "city_path": "location/london/aad17950576b8c448fd4f44dbeb59220",
            "region": "London, City of",
            "region_path": "location/london-city-of/79eb923b9e93e0db2fe075f0c430c2cb",
            "country": "United Kingdom",
            "country_path": "location/united-kingdom/a30e342c17426b1c66e9461de680e54b",
            "latitude": null,
            "longitude": null,
            "created_at": 1378900866,
            "updated_at": 1407435055
          },
          {
            "type": "Address",
            "name": "Norwegian Office",
            "street_1": "Thorvald Meyers gate 70B",
            "street_2": null,
            "postal_code": "0552",
            "city": "Oslo",
            "city_path": "location/oslo/755ee4e5dea64a4d23458583a75e4e81",
            "region": "Oslo",
            "region_path": "location/oslo/55b063f46e9f595837290f5de62c1da8",
            "country": "Norway",
            "country_path": "location/norway/9ae73d3796ed28a846eaf52b26a2f97d",
            "latitude": null,
            "longitude": null,
            "created_at": 1279804669,
            "updated_at": 1397991525
          },
          {
            "type": "Address",
            "name": "Headquarters",
            "street_1": "830 Stewart Dr., Suite 119",
            "street_2": null,
            "postal_code": "CA 94085",
            "city": "Sunnyvale",
            "city_path": "location/sunnyvale/7a65a1f399dedb83a98171b9e0062ba1",
            "region": "California",
            "region_path": "location/california/eb879a83c91a121e0bb8829782dbcf04",
            "country": "United States",
            "country_path": "location/united-states/f110fca2105599f6996d011c198b3928",
            "latitude": null,
            "longitude": null,
            "created_at": 1279804669,
            "updated_at": 1397991524
          }
        ]
      },
      "headquarters": {
        "paging": {
          "total_items": 2,
          "first_page_url": "http://api.crunchbase.com/v/2/organization/altoros-systems/headquarters",
          "sort_order": "created_at DESC"
        },
        "items": [
          {
            "type": "Address",
            "name": "Headquarters",
            "street_1": "830 Stewart Dr., Suite 119",
            "street_2": null,
            "postal_code": "CA 94085",
            "city": "Sunnyvale",
            "city_path": "location/sunnyvale/7a65a1f399dedb83a98171b9e0062ba1",
            "region": "California",
            "region_path": "location/california/eb879a83c91a121e0bb8829782dbcf04",
            "country": "United States",
            "country_path": "location/united-states/f110fca2105599f6996d011c198b3928",
            "latitude": null,
            "longitude": null,
            "created_at": 1279804669,
            "updated_at": 1397991524
          },
          {
            "type": "Address",
            "name": "Headquarters",
            "street_1": "830 Stewart Dr., Suite 119",
            "street_2": null,
            "postal_code": "CA 94085",
            "city": "Sunnyvale",
            "city_path": "location/sunnyvale/7a65a1f399dedb83a98171b9e0062ba1",
            "region": "California",
            "region_path": "location/california/eb879a83c91a121e0bb8829782dbcf04",
            "country": "United States",
            "country_path": "location/united-states/f110fca2105599f6996d011c198b3928",
            "latitude": null,
            "longitude": null,
            "created_at": 1279804669,
            "updated_at": 1397991524
          }
        ]
      },
      "categories": {
        "paging": {
          "total_items": 5,
          "first_page_url": "http://api.crunchbase.com/v/2/organization/altoros-systems/categories",
          "sort_order": "created_at DESC"
        },
        "items": [
          {
            "type": "Category",
            "name": "Big Data",
            "uuid": "c33728a5de33d0da7bce0e3c4383bc99",
            "path": "category/big data/c33728a5de33d0da7bce0e3c4383bc99",
            "created_at": 1397980728,
            "updated_at": 1417089997
          },
          {
            "type": "Category",
            "name": "Big Data Analytics",
            "uuid": "8a60151f6739dde3c98235fcef7a2db8",
            "path": "category/big data analytics/8a60151f6739dde3c98235fcef7a2db8",
            "created_at": 1397980727,
            "updated_at": 1417114221
          },
          {
            "type": "Category",
            "name": "Software",
            "uuid": "c08b5441a05b9777b7a6012728caddd9",
            "path": "category/software/c08b5441a05b9777b7a6012728caddd9",
            "created_at": 1397980727,
            "updated_at": 1417151755
          },
          {
            "type": "Category",
            "name": "Mobile",
            "uuid": "e907cf2a842d8a30a0b107d9de4a8178",
            "path": "category/mobile/e907cf2a842d8a30a0b107d9de4a8178",
            "created_at": 1397980726,
            "updated_at": 1417088485
          },
          {
            "type": "Category",
            "name": "Databases",
            "uuid": "7c5bc9757eb6dbc1f4e77a7867592760",
            "path": "category/databases/7c5bc9757eb6dbc1f4e77a7867592760",
            "created_at": 1397980726,
            "updated_at": 1417114153
          }
        ]
      },
      "founders": {
        "paging": {
          "total_items": 1,
          "first_page_url": "http://api.crunchbase.com/v/2/organization/altoros-systems/founders",
          "sort_order": "created_at DESC"
        },
        "items": [
          {
            "type": "Person",
            "name": "Renat Khasanshyn",
            "path": "person/renat-khasanshyn",
            "created_at": 1297164760,
            "updated_at": 1410041018
          }
        ]
      },
      "primary_image": {
        "paging": {
          "total_items": 1,
          "first_page_url": "http://api.crunchbase.com/v/2/organization/altoros-systems/primary_image",
          "sort_order": "created_at DESC"
        },
        "items": [
          {
            "type": "ImageAsset",
            "title": null,
            "path": "image/upload/v1397187599/1eb9fc970a31044f5cbc8f5a9598206f.gif",
            "created_at": 1398019084,
            "updated_at": 1398019084
          }
        ]
      },
      "images": {
        "paging": {
          "total_items": 7,
          "first_page_url": "http://api.crunchbase.com/v/2/organization/altoros-systems/images",
          "sort_order": "created_at DESC"
        },
        "items": [
          {
            "type": "ImageAsset",
            "title": null,
            "path": "image/upload/v1397187606/852d7c6b05595d9a14738d099283402b.jpg",
            "created_at": 1398019085,
            "updated_at": 1398019085
          },
          {
            "type": "ImageAsset",
            "title": null,
            "path": "image/upload/v1397187605/435d990ddac27b09c671c8b0bfb439f7.jpg",
            "created_at": 1398019085,
            "updated_at": 1398019085
          },
          {
            "type": "ImageAsset",
            "title": null,
            "path": "image/upload/v1397187604/ad75f635cb7ce2e92fe493602b5efe26.jpg",
            "created_at": 1398019084,
            "updated_at": 1398019084
          },
          {
            "type": "ImageAsset",
            "title": null,
            "path": "image/upload/v1397187603/7c41da16baaa139cdee05993570dde75.jpg",
            "created_at": 1398019084,
            "updated_at": 1398019084
          },
          {
            "type": "ImageAsset",
            "title": null,
            "path": "image/upload/v1397187603/247747812946adab0b86896aaf022f21.jpg",
            "created_at": 1398019084,
            "updated_at": 1398019084
          },
          {
            "type": "ImageAsset",
            "title": null,
            "path": "image/upload/v1397187602/989f91fe78449d34620b8fee6372949b.jpg",
            "created_at": 1398019084,
            "updated_at": 1398019084
          },
          {
            "type": "ImageAsset",
            "title": null,
            "path": "image/upload/v1397187601/f3c189b9b2e6b3f4a8fd0e646fc519de.jpg",
            "created_at": 1398019084,
            "updated_at": 1398019084
          }
        ]
      },
      "websites": {
        "paging": {
          "total_items": 6,
          "first_page_url": "http://api.crunchbase.com/v/2/organization/altoros-systems/websites",
          "sort_order": "created_at DESC"
        },
        "items": [
          {
            "url": "http://www.linkedin.com/company/110487",
            "type": "WebPresence",
            "title": "linkedin",
            "created_at": 1397877760,
            "updated_at": 2014
          },
          {
            "url": "http://www.plus.google.com/106511337358259588944",
            "type": "WebPresence",
            "title": "google+",
            "created_at": 1397877760,
            "updated_at": 2014
          },
          {
            "url": "http://www.facebook.com/Altoros",
            "type": "WebPresence",
            "title": "facebook",
            "created_at": 1397877760,
            "updated_at": 2014
          },
          {
            "url": "http://twitter.com/altoros",
            "type": "WebPresence",
            "title": "twitter",
            "created_at": 1279804669,
            "updated_at": 1409420926
          },
          {
            "url": "http://blog.altoros.com/",
            "type": "WebPresence",
            "title": "blog",
            "created_at": 1279804669,
            "updated_at": 1397988651
          },
          {
            "url": "http://www.altoros.com",
            "type": "WebPresence",
            "title": "homepage",
            "created_at": 1279804669,
            "updated_at": 1397988650
          }
        ]
      },
      "news": {
        "paging": {
          "total_items": 4,
          "first_page_url": "http://api.crunchbase.com/v/2/organization/altoros-systems/news",
          "sort_order": "created_at DESC"
        },
        "items": [
          {
            "url": "http://www.networkworld.com/news/tech/2013/062413-hadoop-gpu-271194.html",
            "author": null,
            "posted_on": null,
            "type": "PressReference",
            "title": "Hadoop + GPU: Boost performance of your big data project by 50x-200x?",
            "created_at": 1378901686,
            "updated_at": 2013
          },
          {
            "url": "http://www.networkworld.com/news/tech/2012/120612-hadoop-windows-azure-264867.html",
            "author": null,
            "posted_on": null,
            "type": "PressReference",
            "title": "Hadoop on Windows Azure: Hive vs. JavaScript for processing big data",
            "created_at": 1378901686,
            "updated_at": 2013
          },
          {
            "url": "http://www.networkworld.com/news/tech/2012/071612-cloud-platform-comparison-260923.html",
            "author": null,
            "posted_on": null,
            "type": "PressReference",
            "title": "Cloud platform comparison: CloudStack, Eucalyptus, vCloud Director and OpenStack",
            "created_at": 1378901686,
            "updated_at": 2013
          },
          {
            "url": "http://www.networkworld.com/news/tech/2012/102212-nosql-263595.html",
            "author": null,
            "posted_on": null,
            "type": "PressReference",
            "title": "A vendor-independent comparison of NoSQL databases: Cassandra, HBase, MongoDB, Riak",
            "created_at": 1378901686,
            "updated_at": 2013
          }
        ]
      }
    }
  }
}