{
  "metadata": {
    "version": 2,
    "www_path_prefix": "http://www.crunchbase.com/",
    "api_path_prefix": "http://api.crunchbase.com/v/2/",
    "image_path_prefix": "https://res.cloudinary.com/crunchbase-production/"
  },
  "data": {
    "uuid": "461ee803232308234667d743d53a093d",
    "type": "Organization",
    "properties": {
      "role_company": true,
      "permalink": "ebrandvalue",
      "primary_role": "company",
      "is_closed": false,
      "closed_on_trust_code": 0,
      "name": "eBrandValue\u2122",
      "short_description": "eBrandValue, a web service firm, uses and processes social media-based big data to help companies evaluate their social marketing process.",
      "description": "eBrandValue\u2122 is a web service company that uses and processes social media-based big data to help businesses evaluate their social marketing process. It allows businesses to create effective marketing strategies and measure money on investment.\n\neBrandValue specializes in measuring business strategies, comparing business competitiveness in real time, establishing a proactive management style, and building new competitive intelligence techniques.\n\nIts services benefit companies with an internet existence, such as private universities, FMCGs, automotive, banking, insurance, telecommunications, and retailing.\n",
      "homepage_url": "http://www.ebrandvalue.com",
      "founded_on_day": 1,
      "founded_on_trust_code": 4,
      "founded_on_month": 1,
      "founded_on_year": 2012,
      "founded_on": "2012-01-01",
      "email_address": "marketing@ebrandvalue.com",
      "created_at": 1394457972,
      "updated_at": 1409287531,
      "total_funding_usd": 0,
      "number_of_investments": 0
    },
    "relationships": {
      "offices": {
        "paging": {
          "total_items": 1,
          "first_page_url": "http://api.crunchbase.com/v/2/organization/ebrandvalue/offices",
          "sort_order": "created_at DESC"
        },
        "items": [
          {
            "type": "Address",
            "name": null,
            "street_1": "B\u00fcy\u00fckdere cd. Ecza sk.",
            "street_2": "Safter Is Hani Kat:6 Levent",
            "postal_code": "34410",
            "city": "Istanbul",
            "city_path": "location/istanbul/6618468699ba3fd26be7c4a96c04812a",
            "region": "Istanbul",
            "region_path": "location/istanbul/875467b892a85af41c428e9809f15659",
            "country": "Turkey",
            "country_path": "location/turkey/1fbde7a3631380bfb2e3235b44a89699",
            "latitude": null,
            "longitude": null,
            "created_at": 1394432772,
            "updated_at": 1397993471
          }
        ]
      },
      "headquarters": {
        "paging": {
          "total_items": 1,
          "first_page_url": "http://api.crunchbase.com/v/2/organization/ebrandvalue/headquarters",
          "sort_order": "created_at DESC"
        },
        "items": [
          {
            "type": "Address",
            "name": null,
            "street_1": "B\u00fcy\u00fckdere cd. Ecza sk.",
            "street_2": "Safter Is Hani Kat:6 Levent",
            "postal_code": "34410",
            "city": "Istanbul",
            "city_path": "location/istanbul/6618468699ba3fd26be7c4a96c04812a",
            "region": "Istanbul",
            "region_path": "location/istanbul/875467b892a85af41c428e9809f15659",
            "country": "Turkey",
            "country_path": "location/turkey/1fbde7a3631380bfb2e3235b44a89699",
            "latitude": null,
            "longitude": null,
            "created_at": 1394432772,
            "updated_at": 1397993471
          }
        ]
      },
      "categories": {
        "paging": {
          "total_items": 1,
          "first_page_url": "http://api.crunchbase.com/v/2/organization/ebrandvalue/categories",
          "sort_order": "created_at DESC"
        },
        "items": [
          {
            "type": "Category",
            "name": "Social Media",
            "uuid": "5349a2f214d89727c32a19ebea5db78c",
            "path": "category/social media/5349a2f214d89727c32a19ebea5db78c",
            "created_at": 1397980726,
            "updated_at": 1416995618
          }
        ]
      },
      "primary_image": {
        "paging": {
          "total_items": 1,
          "first_page_url": "http://api.crunchbase.com/v/2/organization/ebrandvalue/primary_image",
          "sort_order": "created_at DESC"
        },
        "items": [
          {
            "type": "ImageAsset",
            "title": null,
            "path": "image/upload/v1397192006/91e1d67556b8ed141d31498652bbc05c.png",
            "created_at": 1398018929,
            "updated_at": 1398018929
          }
        ]
      },
      "images": {
        "paging": {
          "total_items": 1,
          "first_page_url": "http://api.crunchbase.com/v/2/organization/ebrandvalue/images",
          "sort_order": "created_at DESC"
        },
        "items": [
          {
            "type": "ImageAsset",
            "title": null,
            "path": "image/upload/v1397192007/0def54de717229257a04d475856d6d02.png",
            "created_at": 1398018929,
            "updated_at": 1398018929
          }
        ]
      },
      "websites": {
        "paging": {
          "total_items": 6,
          "first_page_url": "http://api.crunchbase.com/v/2/organization/ebrandvalue/websites",
          "sort_order": "created_at DESC"
        },
        "items": [
          {
            "url": "http://www.linkedin.com/company/ebrandvalue",
            "type": "WebPresence",
            "title": "linkedin",
            "created_at": 1406399322,
            "updated_at": 1406399322
          },
          {
            "url": "http://www.facebook.com/eBrandValue",
            "type": "WebPresence",
            "title": "facebook",
            "created_at": 1406399321,
            "updated_at": 1406399321
          },
          {
            "url": "http://vt.webrazzi.com/sirket/ebrandvalue-trade",
            "type": "WebPresence",
            "title": "angellist",
            "created_at": 1397877760,
            "updated_at": 2014
          },
          {
            "url": "http://twitter.com/ebrandvalue",
            "type": "WebPresence",
            "title": "twitter",
            "created_at": 1394432772,
            "updated_at": 1409422770
          },
          {
            "url": "http://www.ebrandvalue.com/category/blog/",
            "type": "WebPresence",
            "title": "blog",
            "created_at": 1394432772,
            "updated_at": 1397988651
          },
          {
            "url": "http://www.ebrandvalue.com",
            "type": "WebPresence",
            "title": "homepage",
            "created_at": 1394432772,
            "updated_at": 1397988651
          }
        ]
      }
    }
  }
}