{
  "metadata": {
    "version": 2,
    "www_path_prefix": "http://www.crunchbase.com/",
    "api_path_prefix": "http://api.crunchbase.com/v/2/",
    "image_path_prefix": "https://res.cloudinary.com/crunchbase-production/"
  },
  "data": {
    "uuid": "867bc6f7c5e4fb2053632b9cb1eb89ef",
    "type": "Organization",
    "properties": {
      "role_company": true,
      "description": "At Iterative, they are building an artificial intelligence big data engine for telecom retailers and their system will provide automated store management functions optimizing each store location remotely. \n",
      "short_description": "Big data analytics engine for brick and mortar retailers",
      "founded_on_day": 1,
      "founded_on_trust_code": 7,
      "founded_on_month": 9,
      "founded_on_year": 2013,
      "founded_on": "2013-09-01",
      "permalink": "iterative",
      "primary_role": "company",
      "is_closed": false,
      "closed_on_trust_code": 0,
      "homepage_url": "http://www.it-erative.com",
      "name": "Iterative",
      "email_address": "prelaunch@iterativepartners.com",
      "closed_on_day": null,
      "closed_on_month": null,
      "closed_on_year": null,
      "closed_on": null,
      "created_at": 1403602983,
      "updated_at": 1416868979,
      "total_funding_usd": 0,
      "number_of_investments": 0
    },
    "relationships": {
      "current_team": {
        "paging": {
          "total_items": 1,
          "first_page_url": "http://api.crunchbase.com/v/2/organization/iterative/current_team",
          "sort_order": "custom"
        },
        "items": [
          {
            "first_name": "Andrei",
            "last_name": "Popovici",
            "title": "Founder",
            "started_on": null,
            "path": "person/andrei-popovici",
            "created_at": 1394825059,
            "updated_at": 1416868978
          }
        ]
      },
      "offices": {
        "paging": {
          "total_items": 3,
          "first_page_url": "http://api.crunchbase.com/v/2/organization/iterative/offices",
          "sort_order": "created_at DESC"
        },
        "items": [
          {
            "type": "Address",
            "name": "USA",
            "street_1": "367 Prince Avenue",
            "street_2": "Suite 2",
            "postal_code": "30601",
            "city": "Athens",
            "city_path": "location/athens/f43966370ed1e7f97f85fc5f0946df8b",
            "region": "Georgia",
            "region_path": "location/georgia/e5e9da40cf545c78963be6d5a2efe686",
            "country": "United States",
            "country_path": "location/united-states/f110fca2105599f6996d011c198b3928",
            "latitude": null,
            "longitude": null,
            "created_at": 1412346053,
            "updated_at": 1412727073
          },
          {
            "type": "Address",
            "name": "UK",
            "street_1": "25 City Road",
            "street_2": "2nd Floor",
            "postal_code": "EC1Y 1AA",
            "city": "London",
            "city_path": "location/london/aad17950576b8c448fd4f44dbeb59220",
            "region": "London, City of",
            "region_path": "location/london-city-of/79eb923b9e93e0db2fe075f0c430c2cb",
            "country": "United Kingdom",
            "country_path": "location/united-kingdom/a30e342c17426b1c66e9461de680e54b",
            "latitude": null,
            "longitude": null,
            "created_at": 1412345980,
            "updated_at": 1412726676
          },
          {
            "type": "Address",
            "name": "Headquarters",
            "street_1": "43 Berkeley Square",
            "street_2": null,
            "postal_code": "W1J 5FJ",
            "city": "London",
            "city_path": "location/london/aad17950576b8c448fd4f44dbeb59220",
            "region": "London, City of",
            "region_path": "location/london-city-of/79eb923b9e93e0db2fe075f0c430c2cb",
            "country": "United Kingdom",
            "country_path": "location/united-kingdom/a30e342c17426b1c66e9461de680e54b",
            "latitude": null,
            "longitude": null,
            "created_at": 1403779354,
            "updated_at": 1407433364
          }
        ]
      },
      "headquarters": {
        "paging": {
          "total_items": 1,
          "first_page_url": "http://api.crunchbase.com/v/2/organization/iterative/headquarters",
          "sort_order": "created_at DESC"
        },
        "items": [
          {
            "type": "Address",
            "name": "Headquarters",
            "street_1": "43 Berkeley Square",
            "street_2": null,
            "postal_code": "W1J 5FJ",
            "city": "London",
            "city_path": "location/london/aad17950576b8c448fd4f44dbeb59220",
            "region": "London, City of",
            "region_path": "location/london-city-of/79eb923b9e93e0db2fe075f0c430c2cb",
            "country": "United Kingdom",
            "country_path": "location/united-kingdom/a30e342c17426b1c66e9461de680e54b",
            "latitude": null,
            "longitude": null,
            "created_at": 1403779354,
            "updated_at": 1407433364
          }
        ]
      },
      "categories": {
        "paging": {
          "total_items": 4,
          "first_page_url": "http://api.crunchbase.com/v/2/organization/iterative/categories",
          "sort_order": "created_at DESC"
        },
        "items": [
          {
            "type": "Category",
            "name": "Artificial Intelligence",
            "uuid": "c4d8caf35fe7359bf9f22d708378e4ee",
            "path": "category/artificial intelligence/c4d8caf35fe7359bf9f22d708378e4ee",
            "created_at": 1397980728,
            "updated_at": 1416999691
          },
          {
            "type": "Category",
            "name": "Big Data",
            "uuid": "c33728a5de33d0da7bce0e3c4383bc99",
            "path": "category/big data/c33728a5de33d0da7bce0e3c4383bc99",
            "created_at": 1397980728,
            "updated_at": 1417159419
          },
          {
            "type": "Category",
            "name": "Machine Learning",
            "uuid": "5ea0cdb7c9a647fc50f8c9b0fac04863",
            "path": "category/machine learning/5ea0cdb7c9a647fc50f8c9b0fac04863",
            "created_at": 1397980727,
            "updated_at": 1417171338
          },
          {
            "type": "Category",
            "name": "Retail Technology",
            "uuid": "93872d37a1f6a0afb9e20b150c79f8eb",
            "path": "category/retail technology/93872d37a1f6a0afb9e20b150c79f8eb",
            "created_at": 1397980727,
            "updated_at": 1417086388
          }
        ]
      },
      "founders": {
        "paging": {
          "total_items": 1,
          "first_page_url": "http://api.crunchbase.com/v/2/organization/iterative/founders",
          "sort_order": "created_at DESC"
        },
        "items": [
          {
            "type": "Person",
            "name": "Andrei Popovici",
            "path": "person/andrei-popovici",
            "created_at": 1394825059,
            "updated_at": 1416868978
          }
        ]
      },
      "primary_image": {
        "paging": {
          "total_items": 1,
          "first_page_url": "http://api.crunchbase.com/v/2/organization/iterative/primary_image",
          "sort_order": "created_at DESC"
        },
        "items": [
          {
            "type": "ImageAsset",
            "title": null,
            "path": "image/upload/v1403602979/hdvidgzwl8ncucfykvjz.jpg",
            "created_at": 1403602983,
            "updated_at": 1403602983
          }
        ]
      },
      "images": {
        "paging": {
          "total_items": 1,
          "first_page_url": "http://api.crunchbase.com/v/2/organization/iterative/images",
          "sort_order": "created_at DESC"
        },
        "items": [
          {
            "type": "ImageAsset",
            "title": null,
            "path": "image/upload/v1403779504/vdfllewbi1oh2bswueo8.png",
            "created_at": 1403779506,
            "updated_at": 1403779506
          }
        ]
      },
      "websites": {
        "paging": {
          "total_items": 4,
          "first_page_url": "http://api.crunchbase.com/v/2/organization/iterative/websites",
          "sort_order": "created_at DESC"
        },
        "items": [
          {
            "url": "http://www.linkedin.com/company/3315146",
            "type": "WebPresence",
            "title": "linkedin",
            "created_at": 1406445932,
            "updated_at": 1406445932
          },
          {
            "url": "http://twitter.com/iterativep",
            "type": "WebPresence",
            "title": "twitter",
            "created_at": 1403779214,
            "updated_at": 1409601529
          },
          {
            "url": "http://www.it-erative.com",
            "type": "WebPresence",
            "title": "homepage",
            "created_at": 1403602983,
            "updated_at": 1403602983
          },
          {
            "url": "https://angel.co/iterative-partners",
            "type": "WebPresence",
            "title": "angellist",
            "created_at": 1397877760,
            "updated_at": 1416868979
          }
        ]
      }
    }
  }
}