{
  "metadata": {
    "version": 2,
    "www_path_prefix": "http://www.crunchbase.com/",
    "api_path_prefix": "http://api.crunchbase.com/v/2/",
    "image_path_prefix": "https://res.cloudinary.com/crunchbase-production/"
  },
  "data": {
    "uuid": "9f6a7daddf8869bb3a796f2573de6c6e",
    "type": "Organization",
    "properties": {
      "description": "The Social Internet funds invests in the primary or secondary shares of rapidly growing tech companies with a focus on mobile, social, cloud, security, big data and crowdfunding.\n",
      "short_description": "The Social Internet Fund invests in shares of growing tech companies focusing on mobile, social, cloud, security, big data and crowdfunding.",
      "founded_on_day": 1,
      "founded_on_trust_code": 6,
      "founded_on_month": 7,
      "founded_on_year": 2012,
      "founded_on": "2012-07-01",
      "permalink": "the-social-internet-fund",
      "primary_role": "investor",
      "is_closed": false,
      "closed_on_trust_code": 0,
      "name": "The Social Internet Fund",
      "closed_on_day": null,
      "closed_on_month": null,
      "closed_on_year": null,
      "closed_on": null,
      "email_address": "lou@socialinternetfund.com",
      "role_investor": true,
      "secondary_role_seed": true,
      "secondary_role_early_stage_venture": true,
      "secondary_role_later_stage_venture": true,
      "sectors": "[\"Advertising\",\"SaaS\",\"Open Source\"]",
      "secondary_role_venture_capital": true,
      "created_at": 1356137845,
      "updated_at": 1416279553,
      "total_funding_usd": 0,
      "number_of_investments": 8
    },
    "relationships": {
      "current_team": {
        "paging": {
          "total_items": 1,
          "first_page_url": "http://api.crunchbase.com/v/2/organization/the-social-internet-fund/current_team",
          "sort_order": "custom"
        },
        "items": [
          {
            "first_name": "Lou",
            "last_name": "Kerner",
            "title": "Founder",
            "started_on": "2012-07-01",
            "path": "person/lou-kerner",
            "created_at": 1280794596,
            "updated_at": 1417019594
          }
        ]
      },
      "members": {
        "paging": {
          "total_items": 1,
          "first_page_url": "http://api.crunchbase.com/v/2/organization/the-social-internet-fund/members",
          "sort_order": "created_at DESC"
        },
        "items": [
          {
            "type": "Organization",
            "name": "CrunchBase Venture Program",
            "path": "organization/crunchbase-venture-program",
            "created_at": 1400105355,
            "updated_at": 1416866514
          }
        ]
      },
      "investments": {
        "paging": {
          "total_items": 8,
          "first_page_url": "http://api.crunchbase.com/v/2/organization/the-social-internet-fund/investments",
          "sort_order": "created_at DESC"
        },
        "items": [
          {
            "type": "InvestorInvestment",
            "money_invested": null,
            "money_invested_currency_code": "USD",
            "money_invested_usd": null,
            "funding_round": {
              "path": "funding-round/f32eb3ac993d1d20bc537411fbb7bbc3"
            },
            "invested_in": {
              "type": "Organization",
              "name": "CapLinked",
              "path": "organization/caplinked"
            }
          },
          {
            "type": "InvestorInvestment",
            "money_invested": null,
            "money_invested_currency_code": "USD",
            "money_invested_usd": null,
            "funding_round": {
              "path": "funding-round/5926679ece5fd71346a02210eb57e67f"
            },
            "invested_in": {
              "type": "Organization",
              "name": "GameSalad",
              "path": "organization/gamesalad"
            }
          },
          {
            "type": "InvestorInvestment",
            "money_invested": null,
            "money_invested_currency_code": "USD",
            "money_invested_usd": null,
            "funding_round": {
              "path": "funding-round/c820c93300521b3f0d290dc94773afc4"
            },
            "invested_in": {
              "type": "Organization",
              "name": "TripleLift",
              "path": "organization/triple-lift"
            }
          },
          {
            "type": "InvestorInvestment",
            "money_invested": null,
            "money_invested_currency_code": "USD",
            "money_invested_usd": null,
            "funding_round": {
              "path": "funding-round/d0a2003b9e14fc981b0ac08aeac62f42"
            },
            "invested_in": {
              "type": "Organization",
              "name": "CoPromote",
              "path": "organization/copromote"
            }
          },
          {
            "type": "InvestorInvestment",
            "money_invested": null,
            "money_invested_currency_code": "USD",
            "money_invested_usd": null,
            "funding_round": {
              "path": "funding-round/57c23e077b448203d1f8a4d4f54c9acf"
            },
            "invested_in": {
              "type": "Organization",
              "name": "Sift Shopping",
              "path": "organization/sift-shopping"
            }
          },
          {
            "type": "InvestorInvestment",
            "money_invested": null,
            "money_invested_currency_code": "USD",
            "money_invested_usd": null,
            "funding_round": {
              "path": "funding-round/348c9e643c30bc6dbcd97dc206a220d3"
            },
            "invested_in": {
              "type": "Organization",
              "name": "Appcelerator",
              "path": "organization/appcelerator"
            }
          },
          {
            "type": "InvestorInvestment",
            "money_invested": null,
            "money_invested_currency_code": "USD",
            "money_invested_usd": null,
            "funding_round": {
              "path": "funding-round/9ec1f48f7d89c9ff25d32670e8678c09"
            },
            "invested_in": {
              "type": "Organization",
              "name": "Optimal, Inc.",
              "path": "organization/optimal"
            }
          },
          {
            "type": "InvestorInvestment",
            "money_invested": null,
            "money_invested_currency_code": "USD",
            "money_invested_usd": null,
            "funding_round": {
              "path": "funding-round/ca6e85ea1be41693da127e2444404ba3"
            },
            "invested_in": {
              "type": "Organization",
              "name": "Yashi",
              "path": "organization/yashi"
            }
          }
        ]
      },
      "founders": {
        "paging": {
          "total_items": 1,
          "first_page_url": "http://api.crunchbase.com/v/2/organization/the-social-internet-fund/founders",
          "sort_order": "created_at DESC"
        },
        "items": [
          {
            "type": "Person",
            "name": "Lou Kerner",
            "path": "person/lou-kerner",
            "created_at": 1280794596,
            "updated_at": 1417019594
          }
        ]
      }
    }
  }
}