{
  "metadata": {
    "version": 2,
    "www_path_prefix": "http://www.crunchbase.com/",
    "api_path_prefix": "http://api.crunchbase.com/v/2/",
    "image_path_prefix": "https://res.cloudinary.com/crunchbase-production/"
  },
  "data": {
    "uuid": "ff010545255ac1282fcc2eda4909bb0a",
    "type": "Organization",
    "properties": {
      "role_company": null,
      "email_address": "bill@workdigital.co.uk",
      "short_description": "Big Data Tech Shop - Purchased by Dice Holdings [NYSE:DHX]",
      "founded_on_day": 1,
      "founded_on_trust_code": 4,
      "founded_on_month": 1,
      "founded_on_year": 2007,
      "founded_on": "2007-01-01",
      "permalink": "workdigital",
      "primary_role": "company",
      "is_closed": false,
      "closed_on_trust_code": 0,
      "homepage_url": "http://workdigital.co.uk",
      "name": "WorkDigital Ltd",
      "closed_on_day": null,
      "closed_on_month": null,
      "closed_on_year": null,
      "closed_on": null,
      "num_employees_min": 11,
      "num_employees_max": 50,
      "description": "WorkDigital Ltd - a big data tech shop that builds and powers enterprise class products making use of proprietary natural language processing algorithms. Machine-learned semantic and metadata layer applied across billions of records. Company was purchased by Dice Holdings Inc. [NYSE:DHX], and has been featured in the NYTimes, the FT, the BBC, WIRED, Guardian, TechCrunch and hundreds of other publications/news outlets.\n",
      "secondary_role_for_profit": true,
      "num_employees_range": null,
      "created_at": 1266347378,
      "updated_at": 1416386439,
      "total_funding_usd": 0,
      "number_of_investments": 0
    },
    "relationships": {
      "current_team": {
        "paging": {
          "total_items": 1,
          "first_page_url": "http://api.crunchbase.com/v/2/organization/workdigital/current_team",
          "sort_order": "custom"
        },
        "items": [
          {
            "first_name": "Jon",
            "last_name": "Cooney",
            "title": "Director",
            "started_on": null,
            "path": "person/jon-cooney",
            "created_at": 1416386329,
            "updated_at": 1416386439
          }
        ]
      },
      "offices": {
        "paging": {
          "total_items": 1,
          "first_page_url": "http://api.crunchbase.com/v/2/organization/workdigital/offices",
          "sort_order": "created_at DESC"
        },
        "items": [
          {
            "type": "Address",
            "name": null,
            "street_1": null,
            "street_2": null,
            "postal_code": null,
            "city": "London",
            "city_path": "location/london/aad17950576b8c448fd4f44dbeb59220",
            "region": "London, City of",
            "region_path": "location/london-city-of/79eb923b9e93e0db2fe075f0c430c2cb",
            "country": "United Kingdom",
            "country_path": "location/united-kingdom/a30e342c17426b1c66e9461de680e54b",
            "latitude": null,
            "longitude": null,
            "created_at": 1266347378,
            "updated_at": 1407433721
          }
        ]
      },
      "headquarters": {
        "paging": {
          "total_items": 1,
          "first_page_url": "http://api.crunchbase.com/v/2/organization/workdigital/headquarters",
          "sort_order": "created_at DESC"
        },
        "items": [
          {
            "type": "Address",
            "name": null,
            "street_1": null,
            "street_2": null,
            "postal_code": null,
            "city": "London",
            "city_path": "location/london/aad17950576b8c448fd4f44dbeb59220",
            "region": "London, City of",
            "region_path": "location/london-city-of/79eb923b9e93e0db2fe075f0c430c2cb",
            "country": "United Kingdom",
            "country_path": "location/united-kingdom/a30e342c17426b1c66e9461de680e54b",
            "latitude": null,
            "longitude": null,
            "created_at": 1266347378,
            "updated_at": 1407433721
          }
        ]
      },
      "categories": {
        "paging": {
          "total_items": 4,
          "first_page_url": "http://api.crunchbase.com/v/2/organization/workdigital/categories",
          "sort_order": "created_at DESC"
        },
        "items": [
          {
            "type": "Category",
            "name": "Big Data",
            "uuid": "c33728a5de33d0da7bce0e3c4383bc99",
            "path": "category/big data/c33728a5de33d0da7bce0e3c4383bc99",
            "created_at": 1397980728,
            "updated_at": 1417159419
          },
          {
            "type": "Category",
            "name": "Semantic Search",
            "uuid": "bb1777e525f3b9f2922b0d5defe0d5bb",
            "path": "category/semantic search/bb1777e525f3b9f2922b0d5defe0d5bb",
            "created_at": 1397980727,
            "updated_at": 1416860458
          },
          {
            "type": "Category",
            "name": "Machine Learning",
            "uuid": "5ea0cdb7c9a647fc50f8c9b0fac04863",
            "path": "category/machine learning/5ea0cdb7c9a647fc50f8c9b0fac04863",
            "created_at": 1397980727,
            "updated_at": 1417171338
          },
          {
            "type": "Category",
            "name": "Search",
            "uuid": "0d39287e5b1377a6970274294daded43",
            "path": "category/search/0d39287e5b1377a6970274294daded43",
            "created_at": 1397980727,
            "updated_at": 1417176163
          }
        ]
      },
      "founders": {
        "paging": {
          "total_items": 2,
          "first_page_url": "http://api.crunchbase.com/v/2/organization/workdigital/founders",
          "sort_order": "created_at DESC"
        },
        "items": [
          {
            "type": "Person",
            "name": "william fischer",
            "path": "person/william-fischer-2",
            "created_at": 1415352657,
            "updated_at": 1415352658
          },
          {
            "type": "Person",
            "name": "Howard Lee",
            "path": "person/howard-lee",
            "created_at": 1205942726,
            "updated_at": 1415352679
          }
        ]
      },
      "products": {
        "paging": {
          "total_items": 3,
          "first_page_url": "http://api.crunchbase.com/v/2/organization/workdigital/products",
          "sort_order": "created_at DESC"
        },
        "items": [
          {
            "type": "Product",
            "name": "DataFreshUp.com",
            "path": "product/datafreshup-com",
            "created_at": 1378414686,
            "updated_at": 1397996112
          },
          {
            "type": "Product",
            "name": "CRMgraph.com",
            "path": "product/crmgraph-com",
            "created_at": 1333393808,
            "updated_at": 1397995439
          },
          {
            "type": "Product",
            "name": "thesocialcv.com",
            "path": "product/thesocialcv-com",
            "created_at": 1333393786,
            "updated_at": 1397995438
          }
        ]
      },
      "primary_image": {
        "paging": {
          "total_items": 1,
          "first_page_url": "http://api.crunchbase.com/v/2/organization/workdigital/primary_image",
          "sort_order": "created_at DESC"
        },
        "items": [
          {
            "type": "ImageAsset",
            "title": null,
            "path": "image/upload/v1397203398/926371a941d3731ccfadb04e8d46a29a.png",
            "created_at": 1398019170,
            "updated_at": 1398019170
          }
        ]
      },
      "websites": {
        "paging": {
          "total_items": 2,
          "first_page_url": "http://api.crunchbase.com/v/2/organization/workdigital/websites",
          "sort_order": "created_at DESC"
        },
        "items": [
          {
            "url": "http://twitter.com/williamfischer",
            "type": "WebPresence",
            "title": "twitter",
            "created_at": 1266347378,
            "updated_at": 1409450825
          },
          {
            "url": "http://workdigital.co.uk",
            "type": "WebPresence",
            "title": "homepage",
            "created_at": 1266347378,
            "updated_at": 1415352576
          }
        ]
      }
    }
  }
}